btcs_crypto_systems/__init__.py
btcs_crypto_systems/address_manangement_service.py
btcs_crypto_systems/token_master.py
btcs_crypto_systems/txstore.py
btcs_crypto_systems/utils.py
btcs_crypto_systems-0.0.16.dist-info/METADATA
btcs_crypto_systems-0.0.16.dist-info/WHEEL
btcs_crypto_systems-0.0.16.dist-info/top_level.txt
btcs_crypto_systems-0.0.16.dist-info/RECORD
