Metadata-Version: 2.1
Name: btcs_crypto_systems
Version: 0.0.16
Summary: To interact with BTCS crypto systems.
Requires-Python: >=3.9
